{
  "site_manifest_cache": {
    "sha": "98dec2969f773a02e17a795eb5959247b7a96743",
    "fetched_at": "2026-07-24T04:20:41.336870+09:00",
    "sites": [
      {
        "name": "VRChatStatus",
        "url": "https://status.vrchat.com/history.rss",
        "handler": "pass_through",
        "interval_sec": 30,
        "tz": "Asia/Tokyo",
        "rss_time_tz": "local"
      },
      {
        "name": "VRChatStatus-ManualGet",
        "url": "https://status.vrchat.com/",
        "handler": "general",
        "interval_sec": 30
      },
      {
        "name": "VRChatStatus.atom",
        "url": "https://status.vrchat.com/history.atom",
        "handler": "pass_through",
        "rss_items": 5,
        "interval_sec": 30,
        "user_agent": "Mozilla/5.0 (Windows NT 10.0; Win64; x64) AppleWebKit/537.36 (KHTML, like Gecko) Chrome/119.0.0.0 Safari/537.36"
      },
      {
        "name": "BoothVRChat-ACC",
        "url": "https://booth.pm/ja/search/VRChat?sort=new&tags%5B%5D=%E3%82%A2%E3%82%AF%E3%82%BB%E3%82%B5%E3%83%AA%E3%83%BC",
        "handler": "booth",
        "rss_items": 30,
        "interval_sec": 120,
        "include_regex": [
          "^https://booth\\.pm/(?:ja/)?items/\\d+$"
        ],
        "exclude_regex": [
          "/users/sign_in",
          "/guide",
          "/about",
          "/carts",
          "^https://booth\\.pm/$"
        ]
      },
      {
        "name": "BoothVRChat-clothe",
        "url": "https://booth.pm/ja/search/VRChat?sort=new&tags%5B%5D=%E8%A1%A3%E8%A3%85",
        "handler": "booth",
        "rss_items": 30,
        "interval_sec": 120,
        "include_regex": [
          "^https://booth\\.pm/(?:ja/)?items/\\d+$"
        ],
        "exclude_regex": [
          "/users/sign_in",
          "/guide",
          "/about",
          "/carts",
          "^https://booth\\.pm/$"
        ]
      },
      {
        "name": "BoothVRChat-world",
        "url": "https://booth.pm/ja/search/%E3%83%AF%E3%83%BC%E3%83%AB%E3%83%89?sort=new&tags%5B%5D=VRChat&tags%5B%5D=World",
        "handler": "booth",
        "rss_items": 30,
        "interval_sec": 120,
        "include_regex": [
          "^https://booth\\.pm/(?:ja/)?items/\\d+$"
        ],
        "exclude_regex": [
          "/users/sign_in",
          "/guide",
          "/about",
          "/carts",
          "^https://booth\\.pm/$"
        ]
      },
      {
        "name": "BoothVRChat-avater",
        "url": "https://booth.pm/ja/items?sort=new&tags%5B%5D=3D%E3%82%AD%E3%83%A3%E3%83%A9%E3%82%AF%E3%82%BF%E3%83%BC&tags%5B%5D=3d%E3%83%A2%E3%83%87%E3%83%AB&tags%5B%5D=VRChat&tags%5B%5D=%E3%82%A2%E3%83%90%E3%82%BF%E3%83%BC",
        "handler": "booth",
        "rss_items": 30,
        "interval_sec": 120,
        "include_regex": [
          "^https://booth\\.pm/(?:ja/)?items/\\d+$"
        ],
        "exclude_regex": [
          "/users/sign_in",
          "/guide",
          "/about",
          "/carts",
          "^https://booth\\.pm/$"
        ]
      },
      {
        "name": "BoothVRChat-SAIL",
        "url": "https://booth.pm/ja/search/%E3%82%BB%E3%83%BC%E3%83%AB?sort=new&tags%5B%5D=VRChat",
        "handler": "booth",
        "rss_items": 30,
        "interval_sec": 120,
        "include_regex": [
          "^https://booth\\.pm/(?:ja/)?items/\\d+$"
        ],
        "exclude_regex": [
          "/users/sign_in",
          "/guide",
          "/about",
          "/carts",
          "^https://booth\\.pm/$"
        ]
      },
      {
        "name": "BoothVRChat-X",
        "url": "https://x.com/BoothVRChat",
        "handler": "twitter",
        "rss_url": "https://rsshub.app/twitter/user/BoothVRChat",
        "rss_items": 30,
        "interval_sec": 300,
        "tz": "Asia/Tokyo",
        "rss_time_tz": "local",
        "min_like_count": 0,
        "min_retweet_count": 0,
        "min_reply_count": 0,
        "min_quote_count": 0
      },
      {
        "name": "CampFireVRChat",
        "url": "https://camp-fire.jp/projects/search?word=VRChat",
        "handler": "general",
        "rss_items": 30,
        "interval_sec": 43200,
        "include_regex": [
          "^https://camp-fire\\.jp/projects/\\d+(/view)?(?:\\?.*)?$",
          "^https://camp-fire\\.jp/projects/view/\\d+(?:\\?.*)?$"
        ],
        "exclude_regex": [
          "^https://camp-fire\\.jp/$",
          "^https://camp-fire\\.jp/projects/(?:search|category)(?:\\?.*)?$",
          "^https://camp-fire\\.jp/(?:project_rewards|creation|furusato|forsocialgood|machi-ya)(?:/|\\?.*)?$",
          "^https://camp-fire\\.jp/(?:help|academy|community|channels|company|privacy|term|news|lp)(?:/|\\?.*)?$",
          "\\?token="
        ]
      }
    ]
  },
  "sites": {
    "VRChatStatus": {
      "last_checked": "2026-07-24T04:20:41.345323+09:00",
      "hash": "4c5a7dbfeb4ac8f0f49a842c2ce3b6b8a99bb8aed7afc5f1acc0ee840fd94c0d",
      "last_updated": "2026-07-09T00:35:10.456910+09:00"
    },
    "VRChatStatus-ManualGet": {
      "last_checked": "2026-07-24T04:20:41.872418+09:00",
      "hash": "844f4e1088f7be539efc0eb8ff5d79c54e3535dbb0890e4b77a344474f75e1ec",
      "last_updated": "2026-07-24T04:20:41.872418+09:00"
    },
    "VRChatStatus.atom": {
      "last_checked": "2026-07-24T04:20:43.399486+09:00",
      "hash": "895b8b3dfe1599be58ddc921cd3a29c01d992c45ccd61da6be7f94f98f92eae9",
      "last_updated": "2026-07-09T00:35:14.179913+09:00"
    },
    "BoothVRChat-ACC": {
      "last_checked": "2026-07-24T04:20:43.869538+09:00",
      "hash": "c3cf68b14ae709638f7c1f7312d1838f2ea90e764a98c13e76f33284c5b24471",
      "last_updated": "2026-07-24T04:20:43.869538+09:00"
    },
    "BoothVRChat-clothe": {
      "last_checked": "2026-07-24T04:21:12.269352+09:00",
      "hash": "909dd4ce2d5505b237c5e231c20541f255fb618204ecd695d32728f2d0e45c69",
      "last_updated": "2026-07-24T04:21:12.269352+09:00"
    },
    "BoothVRChat-world": {
      "last_checked": "2026-07-24T04:21:41.913112+09:00",
      "hash": "6e3f786f9850eb1d74f422bb57ea52e2fffb9c9be6adbd58c59ede5b3a2d934d",
      "last_updated": "2026-07-24T04:21:41.913112+09:00"
    },
    "BoothVRChat-avater": {
      "last_checked": "2026-07-24T04:22:12.297069+09:00",
      "hash": "84479b438ffa15efa3b39a8e300da9ded51ea77f7752d84e48df6bcf3319d1c4",
      "last_updated": "2026-07-24T04:22:12.297069+09:00"
    },
    "CampFireVRChat": {
      "last_checked": "2026-07-23T19:01:10.874158+09:00",
      "hash": "9823fa239455b38fc33b908adce37deb9d335066f82801ba5d36ca89af1c27cb",
      "last_updated": "2026-07-23T19:01:10.874158+09:00"
    },
    "LRCHub-PR": {
      "last_checked": "2026-06-02T22:34:01.443156+09:00"
    },
    "BoothVRChat-SAIL": {
      "last_checked": "2026-07-24T04:22:36.376289+09:00",
      "hash": "714d3c721860f94f469c3ea1bb51997fa6e0a473b3c275c1079b3e24afa93070",
      "last_updated": "2026-07-24T04:22:36.376289+09:00"
    },
    "BoothVRChat-X": {
      "last_checked": "2026-07-24T04:23:00.903302+09:00"
    }
  }
}