{
  "site_manifest_cache": {
    "sha": "98dec2969f773a02e17a795eb5959247b7a96743",
    "fetched_at": "2026-07-06T10:24:20.436002+09:00",
    "sites": [
      {
        "name": "VRChatStatus",
        "url": "https://status.vrchat.com/history.rss",
        "handler": "pass_through",
        "interval_sec": 30,
        "tz": "Asia/Tokyo",
        "rss_time_tz": "local"
      },
      {
        "name": "VRChatStatus-ManualGet",
        "url": "https://status.vrchat.com/",
        "handler": "general",
        "interval_sec": 30
      },
      {
        "name": "VRChatStatus.atom",
        "url": "https://status.vrchat.com/history.atom",
        "handler": "pass_through",
        "rss_items": 5,
        "interval_sec": 30,
        "user_agent": "Mozilla/5.0 (Windows NT 10.0; Win64; x64) AppleWebKit/537.36 (KHTML, like Gecko) Chrome/119.0.0.0 Safari/537.36"
      },
      {
        "name": "BoothVRChat-ACC",
        "url": "https://booth.pm/ja/search/VRChat?sort=new&tags%5B%5D=%E3%82%A2%E3%82%AF%E3%82%BB%E3%82%B5%E3%83%AA%E3%83%BC",
        "handler": "booth",
        "rss_items": 30,
        "interval_sec": 120,
        "include_regex": [
          "^https://booth\\.pm/(?:ja/)?items/\\d+$"
        ],
        "exclude_regex": [
          "/users/sign_in",
          "/guide",
          "/about",
          "/carts",
          "^https://booth\\.pm/$"
        ]
      },
      {
        "name": "BoothVRChat-clothe",
        "url": "https://booth.pm/ja/search/VRChat?sort=new&tags%5B%5D=%E8%A1%A3%E8%A3%85",
        "handler": "booth",
        "rss_items": 30,
        "interval_sec": 120,
        "include_regex": [
          "^https://booth\\.pm/(?:ja/)?items/\\d+$"
        ],
        "exclude_regex": [
          "/users/sign_in",
          "/guide",
          "/about",
          "/carts",
          "^https://booth\\.pm/$"
        ]
      },
      {
        "name": "BoothVRChat-world",
        "url": "https://booth.pm/ja/search/%E3%83%AF%E3%83%BC%E3%83%AB%E3%83%89?sort=new&tags%5B%5D=VRChat&tags%5B%5D=World",
        "handler": "booth",
        "rss_items": 30,
        "interval_sec": 120,
        "include_regex": [
          "^https://booth\\.pm/(?:ja/)?items/\\d+$"
        ],
        "exclude_regex": [
          "/users/sign_in",
          "/guide",
          "/about",
          "/carts",
          "^https://booth\\.pm/$"
        ]
      },
      {
        "name": "BoothVRChat-avater",
        "url": "https://booth.pm/ja/items?sort=new&tags%5B%5D=3D%E3%82%AD%E3%83%A3%E3%83%A9%E3%82%AF%E3%82%BF%E3%83%BC&tags%5B%5D=3d%E3%83%A2%E3%83%87%E3%83%AB&tags%5B%5D=VRChat&tags%5B%5D=%E3%82%A2%E3%83%90%E3%82%BF%E3%83%BC",
        "handler": "booth",
        "rss_items": 30,
        "interval_sec": 120,
        "include_regex": [
          "^https://booth\\.pm/(?:ja/)?items/\\d+$"
        ],
        "exclude_regex": [
          "/users/sign_in",
          "/guide",
          "/about",
          "/carts",
          "^https://booth\\.pm/$"
        ]
      },
      {
        "name": "BoothVRChat-SAIL",
        "url": "https://booth.pm/ja/search/%E3%82%BB%E3%83%BC%E3%83%AB?sort=new&tags%5B%5D=VRChat",
        "handler": "booth",
        "rss_items": 30,
        "interval_sec": 120,
        "include_regex": [
          "^https://booth\\.pm/(?:ja/)?items/\\d+$"
        ],
        "exclude_regex": [
          "/users/sign_in",
          "/guide",
          "/about",
          "/carts",
          "^https://booth\\.pm/$"
        ]
      },
      {
        "name": "BoothVRChat-X",
        "url": "https://x.com/BoothVRChat",
        "handler": "twitter",
        "rss_url": "https://rsshub.app/twitter/user/BoothVRChat",
        "rss_items": 30,
        "interval_sec": 300,
        "tz": "Asia/Tokyo",
        "rss_time_tz": "local",
        "min_like_count": 0,
        "min_retweet_count": 0,
        "min_reply_count": 0,
        "min_quote_count": 0
      },
      {
        "name": "CampFireVRChat",
        "url": "https://camp-fire.jp/projects/search?word=VRChat",
        "handler": "general",
        "rss_items": 30,
        "interval_sec": 43200,
        "include_regex": [
          "^https://camp-fire\\.jp/projects/\\d+(/view)?(?:\\?.*)?$",
          "^https://camp-fire\\.jp/projects/view/\\d+(?:\\?.*)?$"
        ],
        "exclude_regex": [
          "^https://camp-fire\\.jp/$",
          "^https://camp-fire\\.jp/projects/(?:search|category)(?:\\?.*)?$",
          "^https://camp-fire\\.jp/(?:project_rewards|creation|furusato|forsocialgood|machi-ya)(?:/|\\?.*)?$",
          "^https://camp-fire\\.jp/(?:help|academy|community|channels|company|privacy|term|news|lp)(?:/|\\?.*)?$",
          "\\?token="
        ]
      }
    ]
  },
  "sites": {
    "VRChatStatus": {
      "last_checked": "2026-07-06T10:24:20.436431+09:00",
      "hash": "40a9742ad479112357099f27bbe393e7998847dbe5352d0f001b90219bfb0cad",
      "last_updated": "2026-07-06T10:24:20.436431+09:00"
    },
    "VRChatStatus-ManualGet": {
      "last_checked": "2026-07-06T10:24:22.226608+09:00",
      "hash": "55e9870c513bba15c62baba7c86fc36e454945bdde1ba396b277f9def4c1810e",
      "last_updated": "2026-07-06T10:24:22.226608+09:00"
    },
    "VRChatStatus.atom": {
      "last_checked": "2026-07-06T10:24:23.625299+09:00",
      "hash": "e15f644537dcecbce1df6c3d4eab2491a1a2de45e8c01e533f4bf9f5dcea3ae2",
      "last_updated": "2026-07-06T10:24:23.625299+09:00"
    },
    "BoothVRChat-ACC": {
      "last_checked": "2026-07-06T10:24:25.276036+09:00",
      "hash": "da3e4928c8ce27f7e34e2b2119898a46759b2b6fc84c562053dfba0baf3c13d5",
      "last_updated": "2026-07-06T10:24:25.276036+09:00"
    },
    "BoothVRChat-clothe": {
      "last_checked": "2026-07-06T10:24:53.747968+09:00",
      "hash": "2b9adc0178ce62cadb34a408d202b9d54b9e55750df76d6c00c2202466455d6b",
      "last_updated": "2026-07-06T10:24:53.747968+09:00"
    },
    "BoothVRChat-world": {
      "last_checked": "2026-07-06T10:25:25.265086+09:00",
      "hash": "ebbd3848223c4f97065687b3896d9df846191bedf476b2f0872a1968139033d8",
      "last_updated": "2026-07-06T10:25:25.265086+09:00"
    },
    "BoothVRChat-avater": {
      "last_checked": "2026-07-06T10:25:54.578057+09:00",
      "hash": "5db2e7197bdfec3aac7f2892747194615732e76f56ea8ff08168f8fe63c1dd45",
      "last_updated": "2026-07-06T10:25:54.578057+09:00"
    },
    "CampFireVRChat": {
      "last_checked": "2026-07-06T03:20:34.651980+09:00",
      "hash": "3ccdce4272993ef4c2900df850d06ee2224f0cbed26c056f3f0b11babb06a5a2",
      "last_updated": "2026-07-06T03:20:34.651980+09:00"
    },
    "LRCHub-PR": {
      "last_checked": "2026-06-02T22:34:01.443156+09:00"
    },
    "BoothVRChat-SAIL": {
      "last_checked": "2026-07-06T10:26:20.042013+09:00",
      "hash": "c3bc885fd3d159b9dee64cee01642908cfd698a0bce213e02a400836a78b1e10",
      "last_updated": "2026-07-06T10:26:20.042013+09:00"
    },
    "BoothVRChat-X": {
      "last_checked": "2026-07-06T10:26:52.803336+09:00"
    }
  }
}